{
    "manifests": {
        "spomky-labs/lexik-jose-bridge": {
            "manifest": {
                "bundles": {
                    "SpomkyLabs\\LexikJoseBundle\\SpomkyLabsLexikJoseBundle": [
                        "all"
                    ]
                },
                "copy-from-recipe": {
                    "config/": "%CONFIG_DIR%"
                },
                "env": {
                    "SL_JOSE_BRIDGE_SERVER_NAME": "https://www.my-service.com/",
                    "SL_JOSE_BRIDGE_KEY_STORAGE_FOLDER": "/tmp/sl_jose/"
                },
                "post-install-output": [
                    "    Run <comment>make cache-warmup</> to generate keys."
                ]
            },
            "files": {
                "config/packages/spomky_labs_lexik_jose_bridge_bundle.yaml": {
                    "contents": [
                        "lexik_jose:",
                        "    ttl: 1000",
                        "    server_name: '%env(SL_JOSE_BRIDGE_SERVER_NAME)%'",
                        "    key_storage_folder: '%env(SL_JOSE_BRIDGE_KEY_STORAGE_FOLDER)%/'",
                        "    signature_algorithm: 'RS512'",
                        "    signature_key_configuration:",
                        "        kty: 'RSA'",
                        "        size: 4096",
                        "    encryption:",
                        "        enabled: true",
                        "        encryption_key_configuration:",
                        "            kty: 'oct'",
                        "            size: 256",
                        "        key_encryption_algorithm: 'A256KW'",
                        "        content_encryption_algorithm: 'A256CBC-HS512'",
                        ""
                    ],
                    "executable": false
                }
            },
            "ref": "2f4d15bb78275360a38da2897d8736fc2cd8df1b"
        }
    }
}
